extrastats/__init__.py
extrastats/extrastats.py
extrastats-0.1.0.dist-info/METADATA
extrastats-0.1.0.dist-info/WHEEL
extrastats-0.1.0.dist-info/licenses/LICENSE
extrastats-0.1.0.dist-info/RECORD
