Metadata-Version: 2.4
Name: extrastats
Version: 0.1.0
Summary: A Python package for advanced statistical analysis.
Project-URL: Homepage, https://github.com/jerradmgenson/extrastats
Project-URL: Issues, https://github.com/jerradmgenson/extrastats/issues
Author-email: Jerrad Michael Genson <jerradgenson@gmail.com>
License-Expression: MPL-2.0
License-File: LICENSE
Classifier: Operating System :: OS Independent
Classifier: Programming Language :: Python :: 3
Requires-Python: >=3.8
Requires-Dist: joblib==1.4.*
Requires-Dist: numpy==2.2.*
Requires-Dist: packaging==24.*
Requires-Dist: pandas==2.2.*
Requires-Dist: patsy==1.0.*
Requires-Dist: python-dateutil==2.9.0.post0
Requires-Dist: pytz==2024.2
Requires-Dist: scipy==1.15.*
Requires-Dist: six==1.17.*
Requires-Dist: statsmodels==0.14.*
Requires-Dist: tzdata==2025.1
